Metadata-Version: 2.1
Name: cpetreanu-gaussian-binomial
Version: 0.2
Summary: Gaussian distributions
Home-page: UNKNOWN
Author: cpetreanu
Author-email: catanzaropetreanu@gmail.com
License: UNKNOWN
Platform: UNKNOWN
License-File: license.txt
